src/__init__.py
src/core.py
src/main.py
PyPentest-0.4.dist-info/LICENSE.md
PyPentest-0.4.dist-info/METADATA
PyPentest-0.4.dist-info/WHEEL
PyPentest-0.4.dist-info/entry_points.txt
PyPentest-0.4.dist-info/top_level.txt
PyPentest-0.4.dist-info/RECORD
