Metadata-Version: 2.1
Name: PyPentest
Version: 0.4
Summary: PyPentest allow you to perform an NMAP scan on a network
Home-page: http://github.com/CharlesAIMIN/PyPentest
Author: CharlesAIMIN
Author-email: caimin.ing2024@esaip.org
License: UNKNOWN
Platform: UNKNOWN
Classifier: Programming Language :: Python
Requires-Dist: pystyle
Requires-Dist: python-nmap
Requires-Dist: tqdm
